boid_py/__init__.py
boid_py/core.py
boid_py-0.0.2.dist-info/LICENSE
boid_py-0.0.2.dist-info/METADATA
boid_py-0.0.2.dist-info/WHEEL
boid_py-0.0.2.dist-info/top_level.txt
boid_py-0.0.2.dist-info/RECORD
