Metadata-Version: 2.1
Name: boid-py
Version: 0.0.2
Summary: A package for calculating positons of boids
Home-page: https://github.com/syoukera/boid_py
Author: Akira Shioyoke
Author-email: s.akira2986@gmail.com
License: Copyright (c) 2021, Akira Shioyoke
Requires-Dist: numpy
Requires-Dist: cupy
